eformer/__init__.py
eformer/aparser/__init__.py
eformer/aparser/_aparser.py
eformer/common_types.py
eformer/escale/__init__.py
eformer/escale/helpers/__init__.py
eformer/escale/helpers/base.py
eformer/escale/mesh/__init__.py
eformer/escale/mesh/creation.py
eformer/escale/mesh/mesh_helpers.py
eformer/escale/partition/__init__.py
eformer/escale/partition/auto_spec.py
eformer/escale/partition/constraints.py
eformer/escale/partition/manager.py
eformer/executor/__init__.py
eformer/executor/cluster_util.py
eformer/executor/docker_tpu.py
eformer/executor/patch_tpus_ray.py
eformer/executor/ray/__init__.py
eformer/executor/ray/docker_executor.py
eformer/executor/ray/executor.py
eformer/executor/ray/pool_manager.py
eformer/executor/ray/resource_manager.py
eformer/executor/ray/types.py
eformer/jaximus/__init__.py
eformer/jaximus/_imus.py
eformer/loggings.py
eformer/mpric/__init__.py
eformer/mpric/dtypes/__init__.py
eformer/mpric/dtypes/precision_types.py
eformer/mpric/handler/__init__.py
eformer/mpric/handler/precision_handler.py
eformer/mpric/loss_scaling/__init__.py
eformer/mpric/loss_scaling/loss_scaler.py
eformer/mpric/policy/__init__.py
eformer/mpric/policy/policy.py
eformer/ops/__init__.py
eformer/ops/quantization/__init__.py
eformer/ops/quantization/_config.py
eformer/ops/quantization/implicit_array_1bit.py
eformer/ops/quantization/implicit_array_8bit.py
eformer/ops/quantization/implicit_array_nf4.py
eformer/ops/quantization/implicit_array_rsr.py
eformer/ops/quantization/quantization_functions.py
eformer/optimizers/__init__.py
eformer/optimizers/_base.py
eformer/optimizers/_builders.py
eformer/optimizers/_config.py
eformer/optimizers/_factory.py
eformer/optimizers/_tx/__init__.py
eformer/optimizers/_tx/mars.py
eformer/optimizers/_tx/utils.py
eformer/optimizers/_tx/white_kron.py
eformer/paths.py
eformer/py.typed
eformer/pytree/__init__.py
eformer/pytree/_pytree.py
eformer/pytree/_serialization.py
eformer/pytree/_tree_util.py
eformer/pytree/_xtree.py
eformer-0.0.90.dist-info/WHEEL
eformer-0.0.90.dist-info/METADATA
eformer-0.0.90.dist-info/RECORD
