Metadata-Version: 2.3
Name: eformer
Version: 0.0.90
Summary: (EasyDel Former) is a utility library designed to simplify and enhance the development in JAX
Keywords: JAX,Deep Learning,XLA,EasyDeL,Distributed Computing
Author: Erfan Zare Chavoshi
Author-email: Erfan Zare Chavoshi <Erfanzare810@gmail.com>
License: Apache-2.0
Classifier: Development Status :: 3 - Alpha
Classifier: Intended Audience :: Developers
Classifier: Topic :: Scientific/Engineering :: Artificial Intelligence
Classifier: License :: OSI Approved :: Apache Software License
Classifier: Programming Language :: Python :: 3
Classifier: Programming Language :: Python :: 3.11
Classifier: Programming Language :: Python :: 3.12
Classifier: Programming Language :: Python :: 3.13
Requires-Dist: jax>=0.8.2
Requires-Dist: optax>=0.2.2
Requires-Dist: ml-collections==1.1.0
Requires-Dist: plum-dispatch==2.3.2
Requires-Dist: ray[default]>=2.53.0
Requires-Dist: mergedeep~=1.3.4
Requires-Dist: tblib~=3.0.0
Requires-Dist: pyyaml~=6.0.2
Requires-Dist: contextlib2~=21.6.0
Requires-Dist: safetensors>=0.6.2
Requires-Dist: tqdm>=4.67.1
Requires-Dist: psutil>=7.0.0
Requires-Dist: google-cloud-storage>=3.3.0
Requires-Dist: tensorstore>=0.1.76
Requires-Dist: braceexpand>=0.1.7
Requires-Dist: chex>=0.1.91
Requires-Dist: jaxtyping>=0.3.2
Requires-Dist: fsspec[http]>=2024.2,<2026
Requires-Dist: pytest ; extra == 'dev'
Requires-Python: >=3.11, <3.14
Project-URL: Documentation, https://eformer.readthedocs.org/
Project-URL: Homepage, https://github.com/erfanzar/eformer
Project-URL: Repository, https://github.com/erfanzar/eformer
Provides-Extra: dev
